LICENSE
MANIFEST.in
README.rst
setup.py
bin/daemon_fire
bin/fire
bin/fire-chart
docs/Makefile
docs/changelog.rst
docs/conf.py
docs/index.rst
docs/make.bat
firebat/__init__.py
firebat/console/__init__.py
firebat/console/aggr.py
firebat/console/cmd.py
firebat/console/conf.py
firebat/console/defaults.yaml
firebat/console/exceptions.py
firebat/console/phantom.conf.jinja
firebat/console/stepper.py
firebat/result_markdown/about.jinja
firebat/result_markdown/base.jinja
firebat/result_markdown/detailed.jinja
firebat/result_markdown/index.jinja
firebat/result_markdown/css/bootstrap-responsive.css
firebat/result_markdown/css/bootstrap-responsive.min.css
firebat/result_markdown/css/bootstrap.css
firebat/result_markdown/css/bootstrap.min.css
firebat/result_markdown/img/favicon.ico
firebat/result_markdown/img/glyphicons-halflings-white.png
firebat/result_markdown/img/glyphicons-halflings.png
firebat/result_markdown/js/bootstrap-alert.js
firebat/result_markdown/js/bootstrap-button.js
firebat/result_markdown/js/bootstrap-carousel.js
firebat/result_markdown/js/bootstrap-collapse.js
firebat/result_markdown/js/bootstrap-dropdown.js
firebat/result_markdown/js/bootstrap-modal.js
firebat/result_markdown/js/bootstrap-popover.js
firebat/result_markdown/js/bootstrap-scrollspy.js
firebat/result_markdown/js/bootstrap-tab.js
firebat/result_markdown/js/bootstrap-tooltip.js
firebat/result_markdown/js/bootstrap-transition.js
firebat/result_markdown/js/bootstrap-typeahead.js
firebat/result_markdown/js/firebat/init.js
firebat/result_markdown/less/accordion.less
firebat/result_markdown/less/alerts.less
firebat/result_markdown/less/bootstrap.less
firebat/result_markdown/less/breadcrumbs.less
firebat/result_markdown/less/button-groups.less
firebat/result_markdown/less/buttons.less
firebat/result_markdown/less/carousel.less
firebat/result_markdown/less/close.less
firebat/result_markdown/less/code.less
firebat/result_markdown/less/component-animations.less
firebat/result_markdown/less/dropdowns.less
firebat_console.egg-info/PKG-INFO
firebat_console.egg-info/SOURCES.txt
firebat_console.egg-info/dependency_links.txt
firebat_console.egg-info/not-zip-safe
firebat_console.egg-info/requires.txt
firebat_console.egg-info/top_level.txt