Metadata-Version: 1.0
Name: firebat-console
Version: 0.0.11
Summary: Console helpers for Phantom load tool
Home-page: https://github.com/greggyNapalm/firebat_console
Author: Gregory Komissarov
Author-email: gregory.komissarov@gmail.com
License: BSD
Keywords: phantom,firebat
Platform: UNKNOWN
Classifier: Development Status :: 4 - Beta
Classifier: Environment :: Console
Classifier: Intended Audience :: Developers
Classifier: License :: OSI Approved :: BSD License
Classifier: Operating System :: OS Independent
Classifier: Programming Language :: Python :: 2.6
Classifier: Programming Language :: Python :: 2.7
Classifier: Topic :: Software Development :: Testing :: Traffic Generation
